okresult/__init__.py
okresult/error.py
okresult/fn.py
okresult/result.py
okresult/safe.py
okresult-0.4.0.dist-info/METADATA
okresult-0.4.0.dist-info/WHEEL
okresult-0.4.0.dist-info/licenses/LICENSE
okresult-0.4.0.dist-info/RECORD
