Metadata-Version: 2.4
Name: okresult
Version: 0.4.0
Summary: A lightweight Result type for Python.
Project-URL: Homepage, https://github.com/pedrodrocha/okresult
Project-URL: Repository, https://github.com/pedrodrocha/okresult.git
Project-URL: Issues, https://github.com/pedrodrocha/okresult/issues
Author-email: Pedro Rocha <pedro.diniz.rocha@gmail.com>
License: MIT
License-File: LICENSE
Keywords: error-handling,monad,result,type-safety
Classifier: Development Status :: 3 - Alpha
Classifier: Intended Audience :: Developers
Classifier: License :: OSI Approved :: MIT License
Classifier: Programming Language :: Python :: 3
Classifier: Programming Language :: Python :: 3.13
Classifier: Topic :: Software Development :: Libraries
Requires-Python: >=3.13
